dibber/__init__.py
dibber/images.py
dibber/main.py
dibber/settings.py
dibber/utils.py
dibber/validation.py
dibber-1.1.12.dist-info/METADATA
dibber-1.1.12.dist-info/WHEEL
dibber-1.1.12.dist-info/entry_points.txt
dibber-1.1.12.dist-info/licenses/LICENSE.md
dibber-1.1.12.dist-info/RECORD
