Metadata-Version: 2.4
Name: dibber
Version: 1.1.12
Summary: Dibber - Docker image manager
License: BSD
License-File: LICENSE.md
Author: Janne Enberg
Author-email: janne.enberg@lietu.net
Requires-Python: >=3.11
Classifier: License :: Other/Proprietary License
Classifier: Programming Language :: Python :: 3
Classifier: Programming Language :: Python :: 3.11
Classifier: Programming Language :: Python :: 3.12
Classifier: Programming Language :: Python :: 3.13
Classifier: Programming Language :: Python :: 3.14
Requires-Dist: click (>=8.2.1)
Requires-Dist: humanize (>=4.13.0)
Requires-Dist: loguru (>=0.7.3)
Requires-Dist: pathvalidate (>=3.3.1)
Requires-Dist: pydantic (>=2.11.7)
Requires-Dist: pydantic-settings (>=2.10.1)
Requires-Dist: pytest (>=8.4.2)
Requires-Dist: pyyaml (>=6.0.2)
Requires-Dist: typer (>=0.17.4)
